resilient_runner/__init__.py
resilient_runner/runner.py
resilient_runner-0.1.1.dist-info/METADATA
resilient_runner-0.1.1.dist-info/WHEEL
resilient_runner-0.1.1.dist-info/top_level.txt
resilient_runner-0.1.1.dist-info/RECORD
