Metadata-Version: 2.4
Name: resilient-runner
Version: 0.1.1
Summary: An async task runner with concurrency control, retries, and dynamic timeouts.
Author-email: Your Name <you@example.com>
License: MIT
Project-URL: Homepage, https://github.com/yourusername/resilient-runner
Project-URL: Repository, https://github.com/yourusername/resilient-runner
Keywords: asyncio,task runner,concurrency,retry,timeout,resilience
Classifier: Development Status :: 3 - Alpha
Classifier: Intended Audience :: Developers
Classifier: License :: OSI Approved :: MIT License
Classifier: Programming Language :: Python :: 3
Classifier: Programming Language :: Python :: 3.10
Classifier: Programming Language :: Python :: 3.11
Classifier: Programming Language :: Python :: 3.12
Classifier: Operating System :: OS Independent
Classifier: Topic :: Software Development :: Libraries :: Python Modules
Classifier: Framework :: AsyncIO
Requires-Python: >=3.10
